<?xml version="1.0" encoding="utf-8" ?>
<dwsync>
<file name="ui-bg_flat_0_aaaaaa_40x100.png" server="74.63.251.59//www/" local="130603901007871548" remote="130844738400000000" Dst="0" />
<file name="ui-bg_flat_75_ffffff_40x100.png" server="74.63.251.59//www/" local="130603901006488509" remote="130844738400000000" Dst="0" />
<file name="ui-bg_glass_55_fbf9ee_1x400.png" server="74.63.251.59//www/" local="130603901006227902" remote="130844738400000000" Dst="0" />
<file name="ui-bg_glass_65_ffffff_1x400.png" server="74.63.251.59//www/" local="130603901004684082" remote="130844738400000000" Dst="0" />
<file name="ui-bg_glass_75_dadada_1x400.png" server="74.63.251.59//www/" local="130603901004914192" remote="130844738400000000" Dst="0" />
<file name="ui-bg_glass_75_e6e6e6_1x400.png" server="74.63.251.59//www/" local="130603901002989661" remote="130844738400000000" Dst="0" />
<file name="ui-bg_glass_95_fef1ec_1x400.png" server="74.63.251.59//www/" local="130603901003100370" remote="130844738400000000" Dst="0" />
<file name="ui-bg_highlight-soft_75_cccccc_1x100.png" server="74.63.251.59//www/" local="130603901001516821" remote="130844738400000000" Dst="0" />
<file name="ui-icons_222222_256x240.png" server="74.63.251.59//www/" local="130603901001576848" remote="130844738400000000" Dst="0" />
<file name="ui-icons_2e83ff_256x240.png" server="74.63.251.59//www/" local="130603900999682798" remote="130844738400000000" Dst="0" />
<file name="ui-icons_454545_256x240.png" server="74.63.251.59//www/" local="130603900999852910" remote="130844738400000000" Dst="0" />
<file name="ui-icons_888888_256x240.png" server="74.63.251.59//www/" local="130603900997498519" remote="130844738400000000" Dst="0" />
<file name="ui-icons_cd0a0a_256x240.png" server="74.63.251.59//www/" local="130603900995513864" remote="130844738400000000" Dst="0" />
<file name="ui-bg_flat_0_aaaaaa_40x100.png" server="63.143.55.18/www/" local="130603901007871548" remote="131008960800000000" Dst="0" />
<file name="ui-bg_flat_75_ffffff_40x100.png" server="63.143.55.18/www/" local="130603901006488509" remote="131008960800000000" Dst="0" />
<file name="ui-bg_glass_65_ffffff_1x400.png" server="63.143.55.18/www/" local="130603901004684082" remote="131008960800000000" Dst="0" />
<file name="ui-bg_glass_75_dadada_1x400.png" server="63.143.55.18/www/" local="130603901004914192" remote="131008960800000000" Dst="0" />
<file name="ui-bg_glass_55_fbf9ee_1x400.png" server="63.143.55.18/www/" local="130603901006227902" remote="131008960800000000" Dst="0" />
<file name="ui-bg_glass_75_e6e6e6_1x400.png" server="63.143.55.18/www/" local="130603901002989661" remote="131008960800000000" Dst="0" />
<file name="ui-bg_glass_95_fef1ec_1x400.png" server="63.143.55.18/www/" local="130603901003100370" remote="131008960800000000" Dst="0" />
<file name="ui-bg_highlight-soft_75_cccccc_1x100.png" server="63.143.55.18/www/" local="130603901001516821" remote="131008960800000000" Dst="0" />
<file name="ui-icons_2e83ff_256x240.png" server="63.143.55.18/www/" local="130603900999682798" remote="131008960800000000" Dst="0" />
<file name="ui-icons_454545_256x240.png" server="63.143.55.18/www/" local="130603900999852910" remote="131008960800000000" Dst="0" />
<file name="ui-icons_222222_256x240.png" server="63.143.55.18/www/" local="130603901001576848" remote="131008960800000000" Dst="0" />
<file name="ui-icons_cd0a0a_256x240.png" server="63.143.55.18/www/" local="130603900995513864" remote="131008960800000000" Dst="0" />
<file name="ui-icons_888888_256x240.png" server="63.143.55.18/www/" local="130603900997498519" remote="131008960800000000" Dst="0" />
</dwsync>